{
  "conditions": [
    {
      "type": "dym:configuration_option",
      "name": "quark.useQuark",
      "value": true
    },
    {
      "type": "quark:check_boolean_field",
      "class": "vazkii.quark.building.feature.Turf",
      "field": "enableStairsAndSlabs",
      "value": true
    }
  ],
  "requirements": [
    {
      "order": "after",
      "registry_name": "quark:turf",
      "required": true
    }
  ],
  "for": [
    {
      "type": "dym:item",
      "registry_name": "quark:turf"
    },
    {
      "type": "dym:item",
      "registry_name": "quark:turf_stairs"
    },
    {
      "type": "dym:item",
      "registry_name": "quark:turf_slab"
    }
  ],
  "documentation": [
    "dym.doc.quark.turf_stair_slab"
  ]
}
