{
  "conditions": [
    {
      "type": "dym:configuration_option",
      "name": "useTinkersConstruct",
      "value": true
    }
  ],
  "for": [
    {
      "type": "dym:item",
      "registry_name": "tconstruct:slime_channel",
      "metadata": 0
    },
    {
      "type": "dym:item",
      "registry_name": "tconstruct:slime_channel",
      "metadata": 1
    },
    {
      "type": "dym:item",
      "registry_name": "tconstruct:slime_channel",
      "metadata": 2
    },
    {
      "type": "dym:item",
      "registry_name": "tconstruct:slime_channel",
      "metadata": 3
    }
  ],
  "documentation": [
    "dym.doc.tconstruct.slime_channel"
  ]
}
